setup.py
src/pyrbac/__init__.py
src/pyrbac/action.py
src/pyrbac/control.py
src/pyrbac/export.py
src/pyrbac/permission.py
src/pyrbac/resource.py
src/pyrbac/role.py
src/pyrbac/user.py
src/pyrbac.egg-info/PKG-INFO
src/pyrbac.egg-info/SOURCES.txt
src/pyrbac.egg-info/dependency_links.txt
src/pyrbac.egg-info/top_level.txt
src/pyrbac.egg-info/zip-safe
src/tests/__init__.py
src/tests/tests_1.py
src/tests/tests_2.py
src/tests/tests_3.py
src/tests/tests_4.py