Metadata-Version: 1.0
Name: pyrbac
Version: 0.4
Summary: RBAC (Role Based Access Control) library
Home-page: https://github.com/jldupont/pyrbac
Author: Jean-Lou Dupont
Author-email: jl@jldupont.com
License: UNKNOWN
Platform: UNKNOWN
